{
	"name": "relationship-ztsbtujnyx",
	"properties": {
		"Name": "relationship-ztsbtujnyx",
		"EntityType": "RELATIONSHIP",
		"Namespace": {
			"DatabaseName": "Airlines_lcg"
		},
		"Origin": {
			"Type": "SPARK"
		},
		"FromTableName": "Customer",
		"ToTableName": "Order",
		"ColumnRelationshipInformations": [
			{
				"FromColumnName": "CustomerId",
				"ToColumnName": "CustomerId"
			}
		],
		"RelationshipType": 0,
		"Properties": {
			"DerivedModelRelationshipInfo": "{\"baseRelationship\":{\"fromEntity\":\"Customer.cdm.json/Customer\",\"toEntity\":\"Order.cdm.json/Order\",\"joinPairs\":[{\"fromAttribute\":\"CustomerId\",\"toAttribute\":\"CustomerId\"}]}}"
		},
		"PublishStatus": "PUBLISHED",
		"ObjectVersion": 1,
		"ObjectId": "fe12fa72-0deb-4c1a-a011-7bb9134a2602"
	},
	"type": "RELATIONSHIP"
}