{
	"name": "relationship-skntvbhnvu",
	"properties": {
		"Name": "relationship-skntvbhnvu",
		"EntityType": "RELATIONSHIP",
		"Namespace": {
			"DatabaseName": "Airlines_lcg"
		},
		"Origin": {
			"Type": "SPARK"
		},
		"FromTableName": "LegalEntity",
		"ToTableName": "RelatedLegalEntity",
		"ColumnRelationshipInformations": [
			{
				"FromColumnName": "LegalEntityId",
				"ToColumnName": "LegalEntityId"
			}
		],
		"RelationshipType": 0,
		"Properties": {
			"DerivedModelRelationshipInfo": "{\"baseRelationship\":{\"fromEntity\":\"LegalEntity.cdm.json/LegalEntity\",\"toEntity\":\"RelatedLegalEntity.cdm.json/RelatedLegalEntity\",\"joinPairs\":[{\"fromAttribute\":\"LegalEntityId\",\"toAttribute\":\"LegalEntityId\"}]}}"
		},
		"PublishStatus": "PUBLISHED",
		"ObjectVersion": 1,
		"ObjectId": "a79ee23c-bdca-45a1-b50b-82da9efe41bc"
	},
	"type": "RELATIONSHIP"
}