{
	"name": "relationship-nynygzoaoi",
	"properties": {
		"Name": "relationship-nynygzoaoi",
		"EntityType": "RELATIONSHIP",
		"Namespace": {
			"DatabaseName": "Airlines_lcg"
		},
		"Origin": {
			"Type": "SPARK"
		},
		"FromTableName": "LegalEntity",
		"ToTableName": "LegalEntityAccountingPolicy",
		"ColumnRelationshipInformations": [
			{
				"FromColumnName": "LegalEntityId",
				"ToColumnName": "LegalEntityId"
			}
		],
		"RelationshipType": 0,
		"Properties": {
			"DerivedModelRelationshipInfo": "{\"baseRelationship\":{\"fromEntity\":\"LegalEntity.cdm.json/LegalEntity\",\"toEntity\":\"LegalEntityAccountingPolicy.cdm.json/LegalEntityAccountingPolicy\",\"joinPairs\":[{\"fromAttribute\":\"LegalEntityId\",\"toAttribute\":\"LegalEntityId\"}]}}"
		},
		"PublishStatus": "PUBLISHED",
		"ObjectVersion": 1,
		"ObjectId": "77cceebb-cf76-41c1-9a66-fba6c0900b5a"
	},
	"type": "RELATIONSHIP"
}