{
	"name": "relationship-xamdlszcyw",
	"properties": {
		"Name": "relationship-xamdlszcyw",
		"EntityType": "RELATIONSHIP",
		"Namespace": {
			"DatabaseName": "Airlines_lcg"
		},
		"Origin": {
			"Type": "SPARK"
		},
		"FromTableName": "LedgerAccount",
		"ToTableName": "Asset",
		"ColumnRelationshipInformations": [
			{
				"FromColumnName": "LedgerId",
				"ToColumnName": "LedgerId"
			}
		],
		"RelationshipType": 0,
		"Properties": {
			"DerivedModelRelationshipInfo": "{\"baseRelationship\":{\"fromEntity\":\"LedgerAccount.cdm.json/LedgerAccount\",\"toEntity\":\"Asset.cdm.json/Asset\",\"joinPairs\":[{\"fromAttribute\":\"LedgerId\",\"toAttribute\":\"LedgerId\"}]}}"
		},
		"PublishStatus": "PUBLISHED",
		"ObjectVersion": 1,
		"ObjectId": "33ed89f7-037c-4a6c-a52d-a2846c5edff4"
	},
	"type": "RELATIONSHIP"
}