{
	"name": "relationship-qqmjrvexnb",
	"properties": {
		"Name": "relationship-qqmjrvexnb",
		"EntityType": "RELATIONSHIP",
		"Namespace": {
			"DatabaseName": "Retail_Channel"
		},
		"Origin": {
			"Type": "SPARK"
		},
		"FromTableName": "Store",
		"ToTableName": "StoreDepartment",
		"ColumnRelationshipInformations": [
			{
				"FromColumnName": "StoreId",
				"ToColumnName": "StoreId"
			}
		],
		"RelationshipType": 0,
		"Properties": {
			"DerivedModelRelationshipInfo": "{\"baseRelationship\":{\"fromEntity\":\"Store.cdm.json/Store\",\"toEntity\":\"StoreDepartment.cdm.json/StoreDepartment\",\"joinPairs\":[{\"fromAttribute\":\"StoreId\",\"toAttribute\":\"StoreId\"}]}}"
		},
		"PublishStatus": "PUBLISHED",
		"ObjectVersion": 1,
		"ObjectId": "f263cbf7-b681-4fae-8a1d-4ef464c22cd1"
	},
	"type": "RELATIONSHIP"
}